rdf_cty_ccy/__init__.py
rdf_cty_ccy/common/build_onto.py
rdf_cty_ccy/common/fn.py
rdf_cty_ccy/common/monad.py
rdf_cty_ccy/graph/__init__.py
rdf_cty_ccy/graph/binding.py
rdf_cty_ccy/graph/graph.py
rdf_cty_ccy/graph/graph_query.py
rdf_cty_ccy/graph/rdf_prefix.py
rdf_cty_ccy/model/model.py
rdf_cty_ccy/query/query.py
rdf_cty_ccy/rdfdata/ISO3166-1-CountryCodes.ttl
rdf_cty_ccy/rdfdata/ISO4217-CurrencyCodes.ttl
rdf_cty_ccy/rdfdata/__init__.py
rdf_cty_ccy/rdfdata/cty-ccy-rdf.p
rdf_cty_ccy/rdfdata/sfo-currency-extensions.ttl
rdf_cty_ccy-0.1.7.dist-info/entry_points.txt
rdf_cty_ccy-0.1.7.dist-info/WHEEL
rdf_cty_ccy-0.1.7.dist-info/METADATA
rdf_cty_ccy-0.1.7.dist-info/RECORD
