Metadata-Version: 2.1
Name: rdf-cty-ccy
Version: 0.1.7
Summary: Provides the FIBO and OMG Country and Currency Ontology in a queryable form.
Home-page: https://github.com/wildfauve/rdf_cty_ccy
Author: Col Perks
Author-email: wild.fauve@gmail.com
Requires-Python: >=3.9,<4.0
Classifier: Programming Language :: Python :: 3
Classifier: Programming Language :: Python :: 3.9
Classifier: Programming Language :: Python :: 3.10
Requires-Dist: PyMonad (>=2.4.0,<3.0.0)
Requires-Dist: rdflib (>=6.1.1,<7.0.0)
Requires-Dist: requests (>=2.28.1,<3.0.0)
Requires-Dist: simple-memory-cache (>=1.0.0,<2.0.0)
Project-URL: Repository, https://github.com/wildfauve/rdf_cty_ccy
